lotse/__init__.py
lotse/action.py
lotse/context.py
lotse/meta_strategy.py
lotse/strategy.py
lotse/suggestion.py
lotse/app/__init__.py
lotse/app/main.py
lotse/app/guidance_engine/__init__.py
lotse/app/guidance_engine/lotse_engine.py
lotse/app/guidance_engine/socket_manager.py
Lotse-1.0.0.dist-info/LICENSE
Lotse-1.0.0.dist-info/METADATA
Lotse-1.0.0.dist-info/WHEEL
Lotse-1.0.0.dist-info/top_level.txt
Lotse-1.0.0.dist-info/RECORD
