Metadata-Version: 2.1
Name: Lotse
Version: 1.0.0
Summary: A framework for developing strategy-based guidance components for visual analytics components.
Home-page: https://github.com/lotse-guidance/lotse
Author: Fabian Sperrle
Author-email: fabian.sperrle@uni-konstanz.de
License: MIT
Platform: UNKNOWN
Classifier: Development Status :: 2 - Pre-Alpha
Classifier: License :: OSI Approved :: MIT License
Classifier: Programming Language :: Python
Classifier: Programming Language :: Python :: 3
Classifier: Programming Language :: Python :: 3.4
Classifier: Programming Language :: Python :: 3.5
Classifier: Programming Language :: Python :: 3.6
Classifier: Programming Language :: Python :: 3.7
Classifier: Programming Language :: Python :: 3.10
Requires-Dist: fastapi
Requires-Dist: pyyaml
Requires-Dist: requests
Requires-Dist: gsrickled (==1.0.0)
Requires-Dist: starlette
Requires-Dist: pydantic
